CHANGES.rst
LICENSE
MANIFEST.in
README.rst
setup.py
test_transfluent.py
transfluent.py
transfluent.egg-info/PKG-INFO
transfluent.egg-info/SOURCES.txt
transfluent.egg-info/dependency_links.txt
transfluent.egg-info/pbr.json
transfluent.egg-info/requires.txt
transfluent.egg-info/top_level.txt