Metadata-Version: 1.1
Name: transfluent
Version: 0.3.0
Summary: A Python wrapper for Transfluent API
Home-page: http://github.com/jpvanhal/python-transfluent
Author: Janne Vanhala
Author-email: janne.vanhala@gmail.com
License: Copyright (c) 2013-2016 Janne Vanhala
